bifold/__init__.py
bifold/bifold.py
bifold/constants.py
bifold/functions.py
bifold/graph_tools.py
bifold/interactions.py
bifold/matematik.py
bifold/print_tools.py
bifold/time_check.py
bifold/filon/__init__.py
bifold/filon/filon.py
bifold/filon/integrals.py
bifold/simpson/__init__.py
bifold/simpson/integrals.py
bifold/simpson/simpson.py
bifold-0.731.32.dist-info/METADATA
bifold-0.731.32.dist-info/WHEEL
bifold-0.731.32.dist-info/top_level.txt
bifold-0.731.32.dist-info/RECORD
