Metadata-Version: 2.1
Name: bifold
Version: 0.731.32
Summary: BiFold calculates a nuclear potential using the double folding model
Author-email: Mesut Karakoç <mesutkarakoc@gmail.com>
Project-URL: Homepage, https://github.com/mkarakoc/bifold
Classifier: Programming Language :: Python :: 3
Classifier: License :: OSI Approved :: GNU General Public License v3 or later (GPLv3+)
Classifier: Operating System :: OS Independent
Requires-Python: >=3.0
